sshi/__init__.py
sshi/cli.py
sshi-0.1.1.dist-info/WHEEL
sshi-0.1.1.dist-info/entry_points.txt
sshi-0.1.1.dist-info/METADATA
sshi-0.1.1.dist-info/RECORD
