Metadata-Version: 2.3
Name: sshi
Version: 0.1.1
Summary: Tiny SSH instance manager with JSON inventory and completions
Author: Jacob Sun
Author-email: Jacob Sun <jacobsun000@gmail.com>
License: MIT License
Classifier: Programming Language :: Python :: 3
Classifier: License :: OSI Approved :: MIT License
Classifier: Environment :: Console
Classifier: Topic :: System :: Systems Administration
Requires-Python: >=3.8
